scienceio/__init__.py
scienceio/scienceio.py
scienceio-2.2.0.dist-info/WHEEL
scienceio-2.2.0.dist-info/METADATA
scienceio-2.2.0.dist-info/RECORD
