Metadata-Version: 2.1
Name: scienceio
Version: 2.2.0
Summary: ScienceIO Python SDK
Author-email: ScienceIO <info@science.io>
Requires-Python: >=3.7
Classifier: Programming Language :: Python :: 3
Classifier: Operating System :: OS Independent
Requires-Dist: requests >=2.26
Project-URL: Documentation, https://docs.science.io/docs
Project-URL: Home, https://github.com/ScienceIO
Project-URL: Source, https://github.com/ScienceIO/scienceio-python
